pylsci/__init__.py
pylsci/lsci.py
pylsci-1.1.1.dist-info/LICENSE
pylsci-1.1.1.dist-info/METADATA
pylsci-1.1.1.dist-info/WHEEL
pylsci-1.1.1.dist-info/top_level.txt
pylsci-1.1.1.dist-info/RECORD
