Metadata-Version: 2.1
Name: pylsci
Version: 1.1.1
Summary: Python Package for Laser Speckle Contrast Imaging
Author-email: Pascal Keilbach <dev@pk17.org>
License: MIT License        
Project-URL: Homepage, https://github.com/pkeilbach/pylsci
Project-URL: Bug Tracker, https://github.com/pkeilbach/pylsci/issues
Project-URL: Example Notebook, https://mybinder.org/v2/gh/pkeilbach/pylsci/HEAD?labpath=binder%2Fdemo.ipynb
Keywords: pylsci,numpy,laser,speckle,contrast,imaging
Classifier: License :: OSI Approved :: MIT License
Classifier: Programming Language :: Python :: 3
Classifier: Operating System :: OS Independent
Requires-Python: >=3.6
License-File: LICENSE
Requires-Dist: numpy (~=1.23.1)
Provides-Extra: dev
Requires-Dist: black (~=22.6.0) ; extra == 'dev'
Requires-Dist: build (~=0.8.0) ; extra == 'dev'
Requires-Dist: jupyter (~=1.0.0) ; extra == 'dev'
Requires-Dist: matplotlib (~=3.5.2) ; extra == 'dev'
Requires-Dist: mypy (~=0.971) ; extra == 'dev'
Requires-Dist: pre-commit (~=2.20.0) ; extra == 'dev'
Requires-Dist: pylint (~=2.14.5) ; extra == 'dev'
Requires-Dist: twine (~=4.0.1) ; extra == 'dev'
Requires-Dist: wheel (~=0.37.1) ; extra == 'dev'
